{
    "请求头": "手机",
    "主页url": "https://mt23az.vip:9527/",
    "数组": "lazy-image vod-image&&class=\"vod-touch",
    "图片": "http:+div data-original=\"&&\"",
    "标题": "class=\"vod-title\">&&</a>",
    "副标题": "class=\"vod-duration\">&&</span>",
    "简介": "<div class=\"vod-content\"><p>&&</p>",
    "链接": "href=\"&&\"",
    "播放链接": "href=\"&&\"",
    "直接播放": "1",
    "免嗅": "",
    "分类": "國產$guochan#傳媒$chuanmei#日韓$rihan#解說$zongyi#動漫$dongman#歐美$oumei#AI換臉$AIhuanlian#同性$tongxing#三級片$sanjipian",
    "分类url": "https://mt23az.vip:9527/type/{cateId}/---{catePg}/"
}